{
  "db_name": "MySQL",
  "query": "\nINSERT INTO prompts\nSET\n  token = ?,\n  prompt_type = ?,\n\n  maybe_creator_user_token = ?,\n  \n  maybe_model_type = ?,\n  maybe_generation_provider = ?,\n\n  maybe_positive_prompt = ?,\n  maybe_negative_prompt = ?,\n\n  maybe_generation_mode = ?,\n  maybe_aspect_ratio = ?,\n  maybe_resolution = ?,\n  maybe_batch_count = ?,\n  maybe_generate_audio = ?,\n  \n  maybe_other_args = ?,\n\n  creator_ip_address = ?\n        ",
  "describe": {
    "columns": [],
    "parameters": {
      "Right": 14
    },
    "nullable": []
  },
  "hash": "aa2f2e0b259e5512b16aa7c4db1d6e76b5313ed90ffeeed5d70ccaf2953b513f"
}
