{
  "db_name": "MySQL",
  "query": "\nSELECT\n  w2l_templates.token as template_token,\n  w2l_templates.title,\n  w2l_templates.template_type,\n  w2l_templates.duration_millis,\n  w2l_templates.frame_width,\n  w2l_templates.frame_height,\n  w2l_templates.creator_user_token,\n  users.username AS creator_username,\n  users.display_name AS creator_display_name,\n  users.email_gravatar_hash AS creator_gravatar_hash,\n  w2l_templates.created_at\nFROM\n  w2l_templates\nJOIN\n  users\nON\n  users.token = w2l_templates.creator_user_token\nWHERE\n  w2l_templates.is_public_listing_approved IS NULL\n  AND w2l_templates.user_deleted_at IS NULL\n  AND w2l_templates.mod_deleted_at IS NULL\n  AND w2l_templates.is_locked_from_use IS FALSE\n        ",
  "describe": {
    "columns": [
      {
        "ordinal": 0,
        "name": "template_token",
        "type_info": {
          "type": "VarString",
          "flags": "NOT_NULL | UNIQUE_KEY | BINARY | NO_DEFAULT_VALUE",
          "char_set": 224,
          "max_size": 128
        }
      },
      {
        "ordinal": 1,
        "name": "title",
        "type_info": {
          "type": "String",
          "flags": "NOT_NULL | BINARY | NO_DEFAULT_VALUE",
          "char_set": 224,
          "max_size": 1020
        }
      },
      {
        "ordinal": 2,
        "name": "template_type",
        "type_info": {
          "type": "String",
          "flags": "NOT_NULL | MULTIPLE_KEY | BINARY | ENUM",
          "char_set": 224,
          "max_size": 28
        }
      },
      {
        "ordinal": 3,
        "name": "duration_millis",
        "type_info": {
          "type": "Long",
          "flags": "NOT_NULL",
          "char_set": 63,
          "max_size": 10
        }
      },
      {
        "ordinal": 4,
        "name": "frame_width",
        "type_info": {
          "type": "Long",
          "flags": "NOT_NULL",
          "char_set": 63,
          "max_size": 10
        }
      },
      {
        "ordinal": 5,
        "name": "frame_height",
        "type_info": {
          "type": "Long",
          "flags": "NOT_NULL",
          "char_set": 63,
          "max_size": 10
        }
      },
      {
        "ordinal": 6,
        "name": "creator_user_token",
        "type_info": {
          "type": "VarString",
          "flags": "NOT_NULL | MULTIPLE_KEY | BINARY | NO_DEFAULT_VALUE",
          "char_set": 224,
          "max_size": 128
        }
      },
      {
        "ordinal": 7,
        "name": "creator_username",
        "type_info": {
          "type": "VarString",
          "flags": "NOT_NULL | UNIQUE_KEY | BINARY | NO_DEFAULT_VALUE",
          "char_set": 224,
          "max_size": 80
        }
      },
      {
        "ordinal": 8,
        "name": "creator_display_name",
        "type_info": {
          "type": "VarString",
          "flags": "NOT_NULL | BINARY | NO_DEFAULT_VALUE",
          "char_set": 224,
          "max_size": 80
        }
      },
      {
        "ordinal": 9,
        "name": "creator_gravatar_hash",
        "type_info": {
          "type": "String",
          "flags": "NOT_NULL | BINARY | NO_DEFAULT_VALUE",
          "char_set": 224,
          "max_size": 128
        }
      },
      {
        "ordinal": 10,
        "name": "created_at",
        "type_info": {
          "type": "Timestamp",
          "flags": "NOT_NULL | BINARY | TIMESTAMP",
          "char_set": 63,
          "max_size": 19
        }
      }
    ],
    "parameters": {
      "Right": 0
    },
    "nullable": [
      false,
      false,
      false,
      false,
      false,
      false,
      false,
      false,
      false,
      false,
      false
    ]
  },
  "hash": "619d18c87075a86c01f1e0ac26744774293ff8ca6b0011ce611b3f47d8a97a0e"
}
