{
  "db_name": "MySQL",
  "query": "\nINSERT INTO generic_inference_jobs\nSET\n  token = ?,\n  uuid_idempotency_token = ?,\n\n  inference_category = ?,\n  maybe_model_type = ?,\n  maybe_model_token = ?,\n\n  maybe_input_source_token = ?,\n  maybe_input_source_token_type = ?,\n\n  maybe_raw_inference_text = ?,\n\n  maybe_inference_args = ?,\n\n  maybe_creator_user_token = ?,\n  maybe_creator_anonymous_visitor_token = ?,\n  creator_ip_address = ?,\n\n  creator_set_visibility = ?,\n\n  priority_level = ?,\n  is_keepalive_required = ?,\n  max_duration_seconds = ?,\n\n  is_debug_request = ?,\n  maybe_routing_tag = ?,\n\n  status = \"pending\"\n        ",
  "describe": {
    "columns": [],
    "parameters": {
      "Right": 18
    },
    "nullable": []
  },
  "hash": "0d780caac7560f84efb50bd2ed876cbdd728b32e26b73dfbb3009ada12985405"
}
